HSTI/FPI_TMM.py
HSTI/FPI_class.py
HSTI/PCA_class.py
HSTI/TMM_class.py
HSTI/__init__.py
HSTI/animate_data_cube.py
HSTI/basic_math.py
HSTI/black_body_spectrum.py
HSTI/density_scatter_plot.py
HSTI/dsc2numpy.py
HSTI/dsc_class.py
HSTI/fill_gaps.py
HSTI/fpi_gmm.py
HSTI/fpi_sim.py
HSTI/fpi_sim_matrix.py
HSTI/fpi_sim_matrix_angular.py
HSTI/fpi_sim_matrix_no_broadening.py
HSTI/graphene_sensor_TMM.py
HSTI/hsti_export.py
HSTI/hsti_import.py
HSTI/import_camera_response.py
HSTI/import_colormap.py
HSTI/import_mirror_sep.py
HSTI/import_output.py
HSTI/import_pam.py
HSTI/least_squares_methods.py
HSTI/lossy_fpi_sim_matrix.py
HSTI/mirror_sep2wavelength.py
HSTI/mse.py
HSTI/r_sq.py
HSTI/remove_bad_px.py
HSTI/remove_vignetting.py
HSTI/repair_image_defects.py
HSTI/save_band.py
HSTI/spectral_debending.py
HSTI/voronoi_partitioning.py
hsti-0.0.106.dist-info/licenses/LICENSE
hsti-0.0.106.dist-info/METADATA
hsti-0.0.106.dist-info/WHEEL
hsti-0.0.106.dist-info/top_level.txt
hsti-0.0.106.dist-info/RECORD
