Metadata-Version: 2.4
Name: HSTI
Version: 0.0.106
Summary: The NEWTEC HSTI package contains fundamental functions for the data analysis of hyperspectral thermal images (HSTI).
Author: Mads Nibe et. al.
Author-email: mani@newtec.dk
Classifier: Programming Language :: Python :: 3
Classifier: License :: OSI Approved :: MIT License
Classifier: Operating System :: OS Independent
Requires-Python: >=3.6
License-File: LICENSE
Requires-Dist: BaselineRemoval>=0.1.4
Requires-Dist: fast-histogram>=0.10
Requires-Dist: fnnls>=1.0.0
Requires-Dist: ipython>=7.25.0
Requires-Dist: jupyter
Requires-Dist: matplotlib>=3.4.2
Requires-Dist: natsort>=7.1.1
Requires-Dist: notebook>=6.4.0
Requires-Dist: numpy>=1.19.5
Requires-Dist: opencv-python>=4.5.2.54
Requires-Dist: Pillow>=8.4.0
Requires-Dist: scikit-learn>=0.24.2
Requires-Dist: scipy>=1.7.0
Requires-Dist: Screeninfo>=0.8
Requires-Dist: RangeSlider>=2021.7.4
Requires-Dist: tk>=0.1.0
Dynamic: author
Dynamic: author-email
Dynamic: classifier
Dynamic: description
Dynamic: description-content-type
Dynamic: license-file
Dynamic: requires-dist
Dynamic: requires-python
Dynamic: summary
